spaceship/__init__.py
spaceship/control_center/__init__.py
spaceship/control_center/dispatcher.py
spaceship/launchpad/__init__.py
spaceship/launchpad/launcher.py
spaceship-0.0.1.dist-info/LICENSE
spaceship-0.0.1.dist-info/METADATA
spaceship-0.0.1.dist-info/WHEEL
spaceship-0.0.1.dist-info/entry_points.txt
spaceship-0.0.1.dist-info/top_level.txt
spaceship-0.0.1.dist-info/RECORD
