Metadata-Version: 2.1
Name: spaceship
Version: 0.0.1
Summary: Cosmic web-ecosystem
Home-page: UNKNOWN
Author: Pavel Paranin
Author-email: pavel@paran.in
License: UNKNOWN
Platform: UNKNOWN
Classifier: Programming Language :: Python :: 3
Classifier: License :: OSI Approved :: MIT License
Classifier: Operating System :: OS Independent
Requires-Python: >=3.8
